Beautifier/Beautifier.py
Beautifier/__init__.py
valgreen-0.5.data/scripts/valgreen
valgreen-0.5.dist-info/LICENSE
valgreen-0.5.dist-info/METADATA
valgreen-0.5.dist-info/WHEEL
valgreen-0.5.dist-info/top_level.txt
valgreen-0.5.dist-info/RECORD
