Metadata-Version: 2.1
Name: valgreen
Version: 0.5
Summary: Valgrind output readable for human beings 
Home-page: https://github.com/tomasaccini/valgreen/
Author: TomasAccini, FdelMazo
Author-email: UNKNOWN
License: UNKNOWN
Platform: UNKNOWN
Classifier: Programming Language :: Python :: 3
Requires-Dist: colorama
